vmtlib/__init__.py
vmtlib/vmt_file.py
vmtlib/vmt_object.py
vmtlib-0.0.1.dist-info/LICENSE
vmtlib-0.0.1.dist-info/METADATA
vmtlib-0.0.1.dist-info/WHEEL
vmtlib-0.0.1.dist-info/top_level.txt
vmtlib-0.0.1.dist-info/RECORD
