Metadata-Version: 2.1
Name: vmtlib
Version: 0.0.1
Summary: A simple parser for Valve Material Type (.vmt) files.
Home-page: https://github.com/megaprokoli/vmtlib
Author: Philip Meier
License: UNKNOWN
Platform: UNKNOWN
Classifier: Programming Language :: Python :: 3
Classifier: License :: OSI Approved :: MIT License
Classifier: Operating System :: OS Independent
